pheno/crossover.py
pheno/mutation.py
pheno/treegp.py
pheno/trees.py
pheno/typed_trees.py
pheno/__init__.py
pheno-0.1.0.dist-info/DESCRIPTION.rst
pheno-0.1.0.dist-info/METADATA
pheno-0.1.0.dist-info/metadata.json
pheno-0.1.0.dist-info/RECORD
pheno-0.1.0.dist-info/top_level.txt
pheno-0.1.0.dist-info/WHEEL
