Metadata-Version: 2.0
Name: pheno
Version: 0.1.0
Summary: Genetic programming for arbitrary domains
Home-page: https://github.com/hosford42/xcs
Author: Aaron Hosford
Author-email: hosford42@gmail.com
License: Revised BSD
